ddbot/__init__.py
ddbot/app.py
ddbot/lang.py
ddbot/logic.py
due_date_bot-0.1.2.dist-info/entry_points.txt
due_date_bot-0.1.2.dist-info/LICENSE
due_date_bot-0.1.2.dist-info/WHEEL
due_date_bot-0.1.2.dist-info/METADATA
due_date_bot-0.1.2.dist-info/RECORD
